{
    "name": "Skiddo",
    "base_stats": {
        "hp": 66,
        "attack": 65,
        "defense": 48,
        "sp_attack": 62,
        "sp_defense": 57,
        "speed": 52
    },
    "types": [
        "GRASS",
        "GRASS"
    ],
    "abilities": {
        "0": "SAP_SIPPER",
        "1": "NONE",
        "H": "GRASS_PELT"
    },
    "held_items": {
        "50%": "NONE",
        "5%": "NONE"
    },
    "catch_rate": 200,
    "base_exp_reward": 70,
    "ev_yields": {
        "hp": 1,
        "attack": 0,
        "defense": 0,
        "sp_attack": 0,
        "sp_defense": 0,
        "speed": 0
    },
    "gender_ratio": "FEMALE_50",
    "hatch_multiplier": 20,
    "base_happiness": 70,
    "growth_rate": "MEDIUM_FAST",
    "egg_groups": [
        "FIELD",
        "FIELD"
    ],
    "flee_chance": 0,
    "body_color": "BROWN",
    "flip_sprite": false,
    "learnset": {
        "tms": [],
        "level_up": {
            "1": "VINE_WHIP"
        }
    },
    "evolutions": [
        [
            "LEVEL_UP",
            32,
            "GOGOAT"
        ]
    ]
}