{
    "name": "Virizion",
    "base_stats": {
        "hp": 91,
        "attack": 90,
        "defense": 72,
        "sp_attack": 90,
        "sp_defense": 129,
        "speed": 108
    },
    "types": [
        "GRASS",
        "FIGHTING"
    ],
    "abilities": {
        "0": "JUSTIFIED",
        "1": "NONE",
        "H": "NONE"
    },
    "held_items": {
        "50%": "NONE",
        "5%": "NONE"
    },
    "catch_rate": 3,
    "base_exp_reward": 255,
    "ev_yields": {
        "hp": 0,
        "attack": 0,
        "defense": 0,
        "sp_attack": 0,
        "sp_defense": 3,
        "speed": 0
    },
    "gender_ratio": "NO_GENDER",
    "hatch_multiplier": 80,
    "base_happiness": 35,
    "growth_rate": "SLOW",
    "egg_groups": [
        "UNDISCOVERED",
        "UNDISCOVERED"
    ],
    "flee_chance": 0,
    "body_color": "GREEN",
    "flip_sprite": false,
    "learnset": {
        "tms": [],
        "level_up": {
            "1": [
                "VINE_WHIP",
                "KARATE_CHOP"
            ]
        }
    }
}