{
    "name": "Focus Punch",
    "type": "FIGHTING",
    "category": "PHYSICAL",
    "power": 150,
    "accuracy": 100,
    "base_pp": 20,
    "effect": "FOCUS_PUNCH",
    "effect_chance": 0,
    "target_type": "ANY_SINGLE",
    "priority": -3,
    "flags": {
        "make_contact": true,
        "blocked_by_protect": true,
        "bounced_by_magic_coat": false,
        "stolen_by_snatch": false,
        "can_be_mirror_moved": false,
        "triggers_kings_rock": false,
        "animation_hides_hp_bars": false,
        "animation_hides_shadows": true
    },
    "contest_effect": 6,
    "contest_type": 4
}